spg_api/__init__.py
spg_api/analysis.py
spg_api/const.py
spg_api/spg_style.py
spg_api/url_generator.py
spg_api/utils.py
spg_api/views_library.py
spg_api-0.1.2.dist-info/METADATA
spg_api-0.1.2.dist-info/WHEEL
spg_api-0.1.2.dist-info/RECORD
