Metadata-Version: 2.1
Name: spg_api
Version: 0.1.2
Summary: S&P Global API Client
Author: kovzu
Author-email: kovkov@163.com
Requires-Python: >=3.12
Classifier: Programming Language :: Python :: 3
Classifier: Programming Language :: Python :: 3.12
Classifier: Programming Language :: Python :: 3.13
Requires-Dist: matplotlib
Requires-Dist: openpyxl (>=3.0.0)
Requires-Dist: pandas (>=1.5.0)
Requires-Dist: python-dotenv
Requires-Dist: requests (>=2.28.0)
